gwmm/__init__.py
gwmm/__main__.py
gwmm/api_types.py
gwmm/config.py
gwmm/data_classes/__init__.py
gwmm/data_classes/g_node.py
gwmm/data_classes/gps_point.py
gwmm/data_classes/market_type.py
gwmm/enums/__init__.py
gwmm/enums/g_node_role.py
gwmm/enums/g_node_status.py
gwmm/enums/market_price_unit.py
gwmm/enums/market_quantity_unit.py
gwmm/enums/market_type_name.py
gwmm/enums/message_category.py
gwmm/enums/message_category_symbol.py
gwmm/enums/recognized_currency_unit.py
gwmm/enums/universe_type.py
gwmm/market_maker.py
gwmm/market_maker_api.py
gwmm/market_maker_base.py
gwmm/py.typed
gwmm/rest_api.py
gwmm/supervisor.py
gwmm/types/__init__.py
gwmm/types/accepted_bid.py
gwmm/types/atn_bid.py
gwmm/types/g_node_gt.py
gwmm/types/heartbeat_a.py
gwmm/types/latest_price.py
gwmm/types/market_book.py
gwmm/types/market_maker_info.py
gwmm/types/market_price.py
gwmm/types/market_slot.py
gwmm/types/market_type_gt.py
gwmm/types/price_quantity.py
gwmm/types/price_quantity_unitless.py
gwmm/types/ready.py
gwmm/types/sim_timestep.py
gridworks_marketmaker-0.0.3.dist-info/WHEEL
gridworks_marketmaker-0.0.3.dist-info/LICENSE
gridworks_marketmaker-0.0.3.dist-info/METADATA
gridworks_marketmaker-0.0.3.dist-info/entry_points.txt
gridworks_marketmaker-0.0.3.dist-info/RECORD
