Metadata-Version: 2.1
Name: gridworks-marketmaker
Version: 0.0.3
Summary: Gridworks Marketmaker
Home-page: https://github.com/thegridelectric/gridworks-marketmaker
License: MIT
Author: Jessica Millar
Author-email: jmillar@gridworks-consulting.com
Requires-Python: >=3.10,<4.0
Classifier: Development Status :: 2 - Pre-Alpha
Classifier: License :: OSI Approved :: MIT License
Classifier: Programming Language :: Python :: 3
Classifier: Programming Language :: Python :: 3.10
Classifier: Programming Language :: Python :: 3.11
Requires-Dist: gridworks (>=0.1.0,<0.2.0)
Project-URL: Changelog, https://github.com/thegridelectric/gridworks-marketmaker/releases
Project-URL: Documentation, https://gridworks-marketmaker.readthedocs.io
Project-URL: Repository, https://github.com/thegridelectric/gridworks-marketmaker
